<data-definition>
    ----- SKILL -----

    <enum-type type-name='job_skill_class' comment='not in DF'>
        <enum-item name='Normal'/>
        <enum-item name='Medical'/>
        <enum-item name='Personal'/>
        <enum-item name='Social'/>
        <enum-item name='Cultural'/>
        <enum-item name='MilitaryWeapon'/>
        <enum-item name='MilitaryUnarmed'/>
        <enum-item name='MilitaryAttack'/>
        <enum-item name='MilitaryDefense'/>
        <enum-item name='MilitaryMisc'/>
    </enum-type>

    <enum-type type-name='job_skill' base-type='int16_t'> bay12: SkillType
        <enum-attr name='caption'/>
        <enum-attr name='caption_noun'/>
        <enum-attr name='profession' type-name='profession' default-value='NONE'/>
        <enum-attr name='labor' type-name='unit_labor' default-value='NONE'/>
        <enum-attr name='type' type-name='job_skill_class' default-value='Normal'/>

        <enum-item name='NONE' value='-1'/>

        -- 0

        <enum-item name='MINING'>
            <item-attr name='caption' value='Mining'/>
            <item-attr name='caption_noun' value='Miner'/>
            <item-attr name='profession' value='MINER'/>
            <item-attr name='labor' value='MINE'/>
        </enum-item>
        <enum-item name='WOODCUTTING'>
            <item-attr name='caption' value='Wood Cutting'/>
            <item-attr name='caption_noun' value='Wood Cutter'/>
            <item-attr name='profession' value='WOODCUTTER'/>
            <item-attr name='labor' value='CUTWOOD'/>
        </enum-item>
        <enum-item name='CARPENTRY'>
            <item-attr name='caption' value='Carpentry'/>
            <item-attr name='caption_noun' value='Carpenter'/>
            <item-attr name='profession' value='CARPENTER'/>
            <item-attr name='labor' value='CARPENTER'/>
        </enum-item>
        <enum-item name='ENGRAVE_STONE'>
            <item-attr name='caption' value='Engraving'/>
            <item-attr name='caption_noun' value='Engraver'/>
            <item-attr name='profession' value='ENGRAVER'/>
            <item-attr name='labor' value='ENGRAVER'/>
        </enum-item>
        <enum-item name='MASONRY'>
            <item-attr name='caption' value='Masonry'/>
            <item-attr name='caption_noun' value='Mason'/>
            <item-attr name='profession' value='MASON'/>
            <item-attr name='labor' value='MASON'/>
        </enum-item>
        <enum-item name='ANIMALTRAIN'>
            <item-attr name='caption' value='Animal Training'/>
            <item-attr name='caption_noun' value='Animal Trainer'/>
            <item-attr name='profession' value='ANIMAL_TRAINER'/>
            <item-attr name='labor' value='ANIMALTRAIN'/>
        </enum-item>
        <enum-item name='ANIMALCARE'>
            <item-attr name='caption' value='Animal Caretaking'/>
            <item-attr name='caption_noun' value='Animal Caretaker'/>
            <item-attr name='profession' value='ANIMAL_CARETAKER'/>
            <item-attr name='labor' value='ANIMALCARE'/>
        </enum-item>
        <enum-item name='DISSECT_FISH'>
            <item-attr name='caption' value='Fish Dissection'/>
            <item-attr name='caption_noun' value='Fish Dissector'/>
            <item-attr name='profession' value='FISH_DISSECTOR'/>
            <item-attr name='labor' value='DISSECT_FISH'/>
        </enum-item>
        <enum-item name='DISSECT_VERMIN'>
            <item-attr name='caption' value='Animal Dissection'/>
            <item-attr name='caption_noun' value='Animal Dissector'/>
            <item-attr name='profession' value='ANIMAL_DISSECTOR'/>
            <item-attr name='labor' value='DISSECT_VERMIN'/>
        </enum-item>
        <enum-item name='PROCESSFISH'>
            <item-attr name='caption' value='Fish Cleaning'/>
            <item-attr name='caption_noun' value='Fish Cleaner'/>
            <item-attr name='profession' value='FISH_CLEANER'/>
            <item-attr name='labor' value='CLEAN_FISH'/>
        </enum-item>

        -- 10

        <enum-item name='BUTCHER'>
            <item-attr name='caption' value='Butchery'/>
            <item-attr name='caption_noun' value='Butcher'/>
            <item-attr name='profession' value='BUTCHER'/>
            <item-attr name='labor' value='BUTCHER'/>
        </enum-item>
        <enum-item name='TRAPPING'>
            <item-attr name='caption' value='Trapping'/>
            <item-attr name='caption_noun' value='Trapper'/>
            <item-attr name='profession' value='TRAPPER'/>
            <item-attr name='labor' value='TRAPPER'/>
        </enum-item>
        <enum-item name='TANNER'>
            <item-attr name='caption' value='Tanning'/>
            <item-attr name='caption_noun' value='Tanner'/>
            <item-attr name='profession' value='TANNER'/>
            <item-attr name='labor' value='TANNER'/>
        </enum-item>
        <enum-item name='WEAVING'>
            <item-attr name='caption' value='Weaving'/>
            <item-attr name='caption_noun' value='Weaver'/>
            <item-attr name='profession' value='WEAVER'/>
            <item-attr name='labor' value='WEAVER'/>
        </enum-item>
        <enum-item name='BREWING'>
            <item-attr name='caption' value='Brewing'/>
            <item-attr name='caption_noun' value='Brewer'/>
            <item-attr name='profession' value='BREWER'/>
            <item-attr name='labor' value='BREWER'/>
        </enum-item>
        <enum-item name='CLOTHESMAKING'>
            <item-attr name='caption' value='Clothes Making'/>
            <item-attr name='caption_noun' value='Clothier'/>
            <item-attr name='profession' value='CLOTHIER'/>
            <item-attr name='labor' value='CLOTHESMAKER'/>
        </enum-item>
        <enum-item name='MILLING'>
            <item-attr name='caption' value='Milling'/>
            <item-attr name='caption_noun' value='Miller'/>
            <item-attr name='profession' value='MILLER'/>
            <item-attr name='labor' value='MILLER'/>
        </enum-item>
        <enum-item name='PROCESSPLANTS'>
            <item-attr name='caption' value='Threshing'/>
            <item-attr name='caption_noun' value='Thresher'/>
            <item-attr name='profession' value='THRESHER'/>
            <item-attr name='labor' value='PROCESS_PLANT'/>
        </enum-item>
        <enum-item name='CHEESEMAKING'>
            <item-attr name='caption' value='Cheese Making'/>
            <item-attr name='caption_noun' value='Cheese Maker'/>
            <item-attr name='profession' value='CHEESE_MAKER'/>
            <item-attr name='labor' value='MAKE_CHEESE'/>
        </enum-item>

        -- 19

        <enum-item name='MILK'>
            <item-attr name='caption' value='Milking'/>
            <item-attr name='caption_noun' value='Milker'/>
            <item-attr name='profession' value='MILKER'/>
            <item-attr name='labor' value='MILK'/>
        </enum-item>
        <enum-item name='COOK'>
            <item-attr name='caption' value='Cooking'/>
            <item-attr name='caption_noun' value='Cook'/>
            <item-attr name='profession' value='COOK'/>
            <item-attr name='labor' value='COOK'/>
        </enum-item>
        <enum-item name='PLANT'>
            <item-attr name='caption' value='Growing'/>
            <item-attr name='caption_noun' value='Grower'/>
            <item-attr name='profession' value='PLANTER'/>
            <item-attr name='labor' value='PLANT'/>
        </enum-item>
        <enum-item name='HERBALISM'>
            <item-attr name='caption' value='Herbalism'/>
            <item-attr name='caption_noun' value='Herbalist'/>
            <item-attr name='profession' value='HERBALIST'/>
            <item-attr name='labor' value='HERBALIST'/>
        </enum-item>
        <enum-item name='FISH'>
            <item-attr name='caption' value='Fishing'/>
            <item-attr name='caption_noun' value='Fisherman'/>
            <item-attr name='profession' value='FISHERMAN'/>
            <item-attr name='labor' value='FISH'/>
        </enum-item>
        <enum-item name='SMELT'>
            <item-attr name='caption' value='Furnace Operation'/>
            <item-attr name='caption_noun' value='Furnace Operator'/>
            <item-attr name='profession' value='FURNACE_OPERATOR'/>
            <item-attr name='labor' value='SMELT'/>
        </enum-item>
        <enum-item name='EXTRACT_STRAND'>
            <item-attr name='caption' value='Strand Extraction'/>
            <item-attr name='caption_noun' value='Strand Extractor'/>
            <item-attr name='profession' value='STRAND_EXTRACTOR'/>
            <item-attr name='labor' value='EXTRACT_STRAND'/>
        </enum-item>
        <enum-item name='FORGE_WEAPON'>
            <item-attr name='caption' value='Weaponsmithing'/>
            <item-attr name='caption_noun' value='Weaponsmith'/>
            <item-attr name='profession' value='WEAPONSMITH'/>
            <item-attr name='labor' value='FORGE_WEAPON'/>
        </enum-item>
        <enum-item name='FORGE_ARMOR'>
            <item-attr name='caption' value='Armorsmithing'/>
            <item-attr name='caption_noun' value='Armorsmith'/>
            <item-attr name='profession' value='ARMORER'/>
            <item-attr name='labor' value='FORGE_ARMOR'/>
        </enum-item>
        <enum-item name='FORGE_FURNITURE'>
            <item-attr name='caption' value='Metalsmithing'/>
            <item-attr name='caption_noun' value='Metalsmith'/>
            <item-attr name='profession' value='BLACKSMITH'/>
            <item-attr name='labor' value='FORGE_FURNITURE'/>
        </enum-item>

        -- 29

        <enum-item name='CUTGEM'>
            <item-attr name='caption' value='Gem Cutting'/>
            <item-attr name='caption_noun' value='Gem Cutter'/>
            <item-attr name='profession' value='GEM_CUTTER'/>
            <item-attr name='labor' value='CUT_GEM'/>
        </enum-item>
        <enum-item name='ENCRUSTGEM'>
            <item-attr name='caption' value='Gem Setting'/>
            <item-attr name='caption_noun' value='Gem Setter'/>
            <item-attr name='profession' value='GEM_SETTER'/>
            <item-attr name='labor' value='ENCRUST_GEM'/>
        </enum-item>
        <enum-item name='WOODCRAFT'>
            <item-attr name='caption' value='Wood Crafting'/>
            <item-attr name='caption_noun' value='Wood Crafter'/>
            <item-attr name='profession' value='WOODCRAFTER'/>
            <item-attr name='labor' value='WOOD_CRAFT'/>
        </enum-item>
        <enum-item name='STONECRAFT'>
            <item-attr name='caption' value='Stone Crafting'/>
            <item-attr name='caption_noun' value='Stone Crafter'/>
            <item-attr name='profession' value='STONECRAFTER'/>
            <item-attr name='labor' value='STONE_CRAFT'/>
        </enum-item>
        <enum-item name='METALCRAFT'>
            <item-attr name='caption' value='Metal Crafting'/>
            <item-attr name='caption_noun' value='Metal Crafter'/>
            <item-attr name='profession' value='METALCRAFTER'/>
            <item-attr name='labor' value='METAL_CRAFT'/>
        </enum-item>
        <enum-item name='GLASSMAKER'>
            <item-attr name='caption' value='Glassmaking'/>
            <item-attr name='caption_noun' value='Glassmaker'/>
            <item-attr name='profession' value='GLASSMAKER'/>
            <item-attr name='labor' value='GLASSMAKER'/>
        </enum-item>
        <enum-item name='LEATHERWORK'>
            <item-attr name='caption' value='Leatherworkering'/>
            <item-attr name='caption_noun' value='Leatherworker'/>
            <item-attr name='profession' value='LEATHERWORKER'/>
            <item-attr name='labor' value='LEATHER'/>
        </enum-item>
        <enum-item name='BONECARVE'>
            <item-attr name='caption' value='Bone Carving'/>
            <item-attr name='caption_noun' value='Bone Carver'/>
            <item-attr name='profession' value='BONE_CARVER'/>
            <item-attr name='labor' value='BONE_CARVE'/>
        </enum-item>
        <enum-item name='AXE'>
            <item-attr name='caption' value='Axe'/>
            <item-attr name='caption_noun' value='Axeman'/>
            <item-attr name='profession' value='AXEMAN'/>
            <item-attr name='type' value='MilitaryWeapon'/>
        </enum-item>
        <enum-item name='SWORD'>
            <item-attr name='caption' value='Sword'/>
            <item-attr name='caption_noun' value='Swordsman'/>
            <item-attr name='profession' value='SWORDSMAN'/>
            <item-attr name='type' value='MilitaryWeapon'/>
        </enum-item>

        -- 39

        <enum-item name='DAGGER'>
            <item-attr name='caption' value='Knife'/>
            <item-attr name='caption_noun' value='Knife User'/>
            <item-attr name='type' value='MilitaryWeapon'/>
        </enum-item>
        <enum-item name='MACE'>
            <item-attr name='caption' value='Mace'/>
            <item-attr name='caption_noun' value='Maceman'/>
            <item-attr name='profession' value='MACEMAN'/>
            <item-attr name='type' value='MilitaryWeapon'/>
        </enum-item>
        <enum-item name='HAMMER'>
            <item-attr name='caption' value='Hammer'/>
            <item-attr name='caption_noun' value='Hammerman'/>
            <item-attr name='profession' value='HAMMERMAN'/>
            <item-attr name='type' value='MilitaryWeapon'/>
        </enum-item>
        <enum-item name='SPEAR'>
            <item-attr name='caption' value='Spear'/>
            <item-attr name='caption_noun' value='Spearman'/>
            <item-attr name='profession' value='SPEARMAN'/>
            <item-attr name='type' value='MilitaryWeapon'/>
        </enum-item>
        <enum-item name='CROSSBOW'>
            <item-attr name='caption' value='Crossbow'/>
            <item-attr name='caption_noun' value='Crossbowman'/>
            <item-attr name='profession' value='CROSSBOWMAN'/>
            <item-attr name='labor' value='HUNT'/>
            <item-attr name='type' value='MilitaryWeapon'/>
        </enum-item>
        <enum-item name='SHIELD'>
            <item-attr name='caption' value='Shield'/>
            <item-attr name='caption_noun' value='Shield User'/>
            <item-attr name='type' value='MilitaryDefense'/>
        </enum-item>
        <enum-item name='ARMOR'>
            <item-attr name='caption' value='Armor'/>
            <item-attr name='caption_noun' value='Armor User'/>
            <item-attr name='type' value='MilitaryDefense'/>
        </enum-item>
        <enum-item name='SIEGECRAFT'>
            <item-attr name='caption' value='Siege Engineering'/>
            <item-attr name='caption_noun' value='Siege Engineer'/>
            <item-attr name='profession' value='SIEGE_ENGINEER'/>
            <item-attr name='labor' value='SIEGECRAFT'/>
        </enum-item>
        <enum-item name='SIEGEOPERATE'>
            <item-attr name='caption' value='Siege Operation'/>
            <item-attr name='caption_noun' value='Siege Operator'/>
            <item-attr name='profession' value='SIEGE_OPERATOR'/>
            <item-attr name='labor' value='SIEGEOPERATE'/>
        </enum-item>
        <enum-item name='BOWYER'>
            <item-attr name='caption' value='Bowmaking'/>
            <item-attr name='caption_noun' value='Bowyer'/>
            <item-attr name='profession' value='BOWYER'/>
            <item-attr name='labor' value='BOWYER'/>
        </enum-item>

        -- 49

        <enum-item name='PIKE'>
            <item-attr name='caption' value='Pike'/>
            <item-attr name='caption_noun' value='Pikeman'/>
            <item-attr name='profession' value='PIKEMAN'/>
            <item-attr name='type' value='MilitaryWeapon'/>
        </enum-item>
        <enum-item name='WHIP'>
            <item-attr name='caption' value='Lash'/>
            <item-attr name='caption_noun' value='Lasher'/>
            <item-attr name='profession' value='LASHER'/>
            <item-attr name='type' value='MilitaryWeapon'/>
        </enum-item>
        <enum-item name='BOW'>
            <item-attr name='caption' value='Bow'/>
            <item-attr name='caption_noun' value='Bowman'/>
            <item-attr name='profession' value='BOWMAN'/>
            <item-attr name='labor' value='HUNT'/>
            <item-attr name='type' value='MilitaryWeapon'/>
        </enum-item>
        <enum-item name='BLOWGUN'>
            <item-attr name='caption' value='Blowgun'/>
            <item-attr name='caption_noun' value='Blowgunner'/>
            <item-attr name='profession' value='BLOWGUNMAN'/>
            <item-attr name='type' value='MilitaryWeapon'/>
        </enum-item>
        <enum-item name='THROW'>
            <item-attr name='caption' value='Throwing'/>
            <item-attr name='caption_noun' value='Thrower'/>
            <item-attr name='type' value='MilitaryAttack'/>
        </enum-item>
        <enum-item name='MECHANICS'>
            <item-attr name='caption' value='Machinery'/>
            <item-attr name='caption_noun' value='Mechanic'/>
            <item-attr name='profession' value='MECHANIC'/>
            <item-attr name='labor' value='MECHANIC'/>
        </enum-item>
        <enum-item name='MAGIC_NATURE'>
            <item-attr name='caption' value='Nature'/>
            <item-attr name='caption_noun' value='Druid'/>
        </enum-item>
        <enum-item name='SNEAK'>
            <item-attr name='caption' value='Ambush'/>
            <item-attr name='caption_noun' value='Ambusher'/>
            <item-attr name='profession' value='HUNTER'/>
            <item-attr name='labor' value='HUNT'/>
        </enum-item>
        <enum-item name='DRESS_WOUNDS'>
            <item-attr name='caption' value='Wound Dressing'/>
            <item-attr name='caption_noun' value='Wound Dresser'/>
            <item-attr name='labor' value='DRESSING_WOUNDS'/>
            <item-attr name='type' value='Medical'/>
        </enum-item>

        -- 58

        <enum-item name='DIAGNOSE'>
            <item-attr name='caption' value='Diagnostics'/>
            <item-attr name='caption_noun' value='Diagnostician'/>
            <item-attr name='profession' value='DIAGNOSER'/>
            <item-attr name='labor' value='DIAGNOSE'/>
            <item-attr name='type' value='Medical'/>
        </enum-item>
        <enum-item name='SURGERY'>
            <item-attr name='caption' value='Surgery'/>
            <item-attr name='caption_noun' value='Surgeon'/>
            <item-attr name='profession' value='SURGEON'/>
            <item-attr name='labor' value='SURGERY'/>
            <item-attr name='type' value='Medical'/>
        </enum-item>
        <enum-item name='SET_BONE'>
            <item-attr name='caption' value='Bone Setting'/>
            <item-attr name='caption_noun' value='Bone Doctor'/>
            <item-attr name='profession' value='BONE_SETTER'/>
            <item-attr name='labor' value='BONE_SETTING'/>
            <item-attr name='type' value='Medical'/>
        </enum-item>
        <enum-item name='SUTURE'>
            <item-attr name='caption' value='Suturing'/>
            <item-attr name='caption_noun' value='Suturer'/>
            <item-attr name='profession' value='SUTURER'/>
            <item-attr name='labor' value='SUTURING'/>
            <item-attr name='type' value='Medical'/>
        </enum-item>
        <enum-item name='CRUTCH_WALK'>
            <item-attr name='caption' value='Crutch-walking'/>
            <item-attr name='caption_noun' value='Crutch-walker'/>
            <item-attr name='type' value='Personal'/>
        </enum-item>
        <enum-item name='WOOD_BURNING'>
            <item-attr name='caption' value='Wood Burning'/>
            <item-attr name='caption_noun' value='Wood Burner'/>
            <item-attr name='profession' value='WOOD_BURNER'/>
            <item-attr name='labor' value='BURN_WOOD'/>
        </enum-item>
        <enum-item name='LYE_MAKING'>
            <item-attr name='caption' value='Lye Making'/>
            <item-attr name='caption_noun' value='Lye Maker'/>
            <item-attr name='profession' value='LYE_MAKER'/>
            <item-attr name='labor' value='LYE_MAKING'/>
        </enum-item>
        <enum-item name='SOAP_MAKING'>
            <item-attr name='caption' value='Soap Making'/>
            <item-attr name='caption_noun' value='Soaper'/>
            <item-attr name='profession' value='SOAP_MAKER'/>
            <item-attr name='labor' value='SOAP_MAKER'/>
        </enum-item>
        <enum-item name='POTASH_MAKING'>
            <item-attr name='caption' value='Potash Making'/>
            <item-attr name='caption_noun' value='Potash Maker'/>
            <item-attr name='profession' value='POTASH_MAKER'/>
            <item-attr name='labor' value='POTASH_MAKING'/>
        </enum-item>
        <enum-item name='DYER'>
            <item-attr name='caption' value='Dyeing'/>
            <item-attr name='caption_noun' value='Dyer'/>
            <item-attr name='profession' value='DYER'/>
            <item-attr name='labor' value='DYER'/>
        </enum-item>

        -- 68

        <enum-item name='OPERATE_PUMP'>
            <item-attr name='caption' value='Pump Operation'/>
            <item-attr name='caption_noun' value='Pump Operator'/>
            <item-attr name='profession' value='PUMP_OPERATOR'/>
            <item-attr name='labor' value='OPERATE_PUMP'/>
        </enum-item>
        <enum-item name='SWIMMING'>
            <item-attr name='caption' value='Swimming'/>
            <item-attr name='caption_noun' value='Swimmer'/>
            <item-attr name='type' value='Personal'/>
        </enum-item>
        <enum-item name='PERSUASION'>
            <item-attr name='caption' value='Persuasion'/>
            <item-attr name='caption_noun' value='Persuader'/>
            <item-attr name='type' value='Social'/>
        </enum-item>
        <enum-item name='NEGOTIATION'>
            <item-attr name='caption' value='Negotiation'/>
            <item-attr name='caption_noun' value='Negotiator'/>
            <item-attr name='type' value='Social'/>
        </enum-item>
        <enum-item name='JUDGING_INTENT'>
            <item-attr name='caption' value='Judging Intent'/>
            <item-attr name='caption_noun' value='Judge of Intent'/>
            <item-attr name='type' value='Social'/>
        </enum-item>
        <enum-item name='APPRAISAL'>
            <item-attr name='caption' value='Appraisal'/>
            <item-attr name='caption_noun' value='Appraiser'/>
            <item-attr name='profession' value='TRADER'/>
        </enum-item>
        <enum-item name='ORGANIZATION'>
            <item-attr name='caption' value='Organization'/>
            <item-attr name='caption_noun' value='Organizer'/>
            <item-attr name='profession' value='ADMINISTRATOR'/>
        </enum-item>
        <enum-item name='RECORD_KEEPING'>
            <item-attr name='caption' value='Record Keeping'/>
            <item-attr name='caption_noun' value='Record Keeper'/>
            <item-attr name='profession' value='CLERK'/>
        </enum-item>
        <enum-item name='LYING'>
            <item-attr name='caption' value='Lying'/>
            <item-attr name='caption_noun' value='Liar'/>
            <item-attr name='type' value='Social'/>
        </enum-item>
        <enum-item name='INTIMIDATION'>
            <item-attr name='caption' value='Intimidation'/>
            <item-attr name='caption_noun' value='Intimidator'/>
            <item-attr name='type' value='Social'/>
        </enum-item>

        -- 78

        <enum-item name='CONVERSATION'>
            <item-attr name='caption' value='Conversation'/>
            <item-attr name='caption_noun' value='Conversationalist'/>
            <item-attr name='type' value='Social'/>
        </enum-item>
        <enum-item name='COMEDY'>
            <item-attr name='caption' value='Comedy'/>
            <item-attr name='caption_noun' value='Comedian'/>
            <item-attr name='type' value='Social'/>
        </enum-item>
        <enum-item name='FLATTERY'>
            <item-attr name='caption' value='Flattery'/>
            <item-attr name='caption_noun' value='Flatterer'/>
            <item-attr name='type' value='Social'/>
        </enum-item>
        <enum-item name='CONSOLE'>
            <item-attr name='caption' value='Consoling'/>
            <item-attr name='caption_noun' value='Consoler'/>
            <item-attr name='type' value='Social'/>
        </enum-item>
        <enum-item name='PACIFY'>
            <item-attr name='caption' value='Pacification'/>
            <item-attr name='caption_noun' value='Pacifier'/>
            <item-attr name='type' value='Social'/>
        </enum-item>
        <enum-item name='TRACKING'>
            <item-attr name='caption' value='Tracking'/>
            <item-attr name='caption_noun' value='Tracker'/>
            <item-attr name='type' value='Personal'/>
        </enum-item>
        <enum-item name='KNOWLEDGE_ACQUISITION'>
            <item-attr name='caption' value='Studying'/>
            <item-attr name='caption_noun' value='Student'/>
            <item-attr name='type' value='Social'/>
        </enum-item>
        <enum-item name='CONCENTRATION'>
            <item-attr name='caption' value='Concentration'/>
            <item-attr name='caption_noun' value='Concentration'/>
            <item-attr name='type' value='Personal'/>
        </enum-item>
        <enum-item name='DISCIPLINE'>
            <item-attr name='caption' value='Discipline'/>
            <item-attr name='caption_noun' value='Discipline'/>
            <item-attr name='type' value='Personal'/>
        </enum-item>
        <enum-item name='SITUATIONAL_AWARENESS'>
            <item-attr name='caption' value='Observation'/>
            <item-attr name='caption_noun' value='Observer'/>
            <item-attr name='type' value='Personal'/>
        </enum-item>

        -- 88

        <enum-item name='WRITING'>
            <item-attr name='caption' value='Writing'/>
            <item-attr name='caption_noun' value='Wordsmith'/>
            <item-attr name='type' value='Cultural'/>
        </enum-item>
        <enum-item name='PROSE'>
            <item-attr name='caption' value='Prose'/>
            <item-attr name='caption_noun' value='Writer'/>
            <item-attr name='type' value='Cultural'/>
        </enum-item>
        <enum-item name='POETRY'>
            <item-attr name='caption' value='Poetry'/>
            <item-attr name='caption_noun' value='Poet'/>
            <item-attr name='profession' value='POET'/>
            <item-attr name='type' value='Cultural'/>
        </enum-item>
        <enum-item name='READING'>
            <item-attr name='caption' value='Reading'/>
            <item-attr name='caption_noun' value='Reader'/>
            <item-attr name='type' value='Cultural'/>
        </enum-item>
        <enum-item name='SPEAKING'>
            <item-attr name='caption' value='Speaking'/>
            <item-attr name='caption_noun' value='Speaker'/>
            <item-attr name='type' value='Cultural'/>
        </enum-item>
        <enum-item name='COORDINATION'>
            <item-attr name='caption' value='Coordination'/>
            <item-attr name='caption_noun' value='Coordination'/>
            <item-attr name='type' value='Personal'/>
        </enum-item>
        <enum-item name='BALANCE'>
            <item-attr name='caption' value='Balance'/>
            <item-attr name='caption_noun' value='Balance'/>
            <item-attr name='type' value='Personal'/>
        </enum-item>
        <enum-item name='LEADERSHIP'>
            <item-attr name='caption' value='Leadership'/>
            <item-attr name='caption_noun' value='Leader'/>
            <item-attr name='type' value='Social'/>
        </enum-item>
        <enum-item name='TEACHING'>
            <item-attr name='caption' value='Teaching'/>
            <item-attr name='caption_noun' value='Teacher'/>
            <item-attr name='type' value='Social'/>
        </enum-item>
        <enum-item name='MELEE_COMBAT'>
            <item-attr name='caption' value='Fighting'/>
            <item-attr name='caption_noun' value='Fighter'/>
            <item-attr name='type' value='MilitaryAttack'/>
        </enum-item>

        -- 98

        <enum-item name='RANGED_COMBAT'>
            <item-attr name='caption' value='Archery'/>
            <item-attr name='caption_noun' value='Archer'/>
            <item-attr name='labor' value='HUNT'/>
            <item-attr name='type' value='MilitaryAttack'/>
        </enum-item>
        <enum-item name='WRESTLING'>
            <item-attr name='caption' value='Wrestling'/>
            <item-attr name='caption_noun' value='Wrestler'/>
            <item-attr name='profession' value='WRESTLER'/>
            <item-attr name='type' value='MilitaryUnarmed'/>
        </enum-item>
        <enum-item name='BITE'>
            <item-attr name='caption' value='Biting'/>
            <item-attr name='caption_noun' value='Biter'/>
            <item-attr name='type' value='MilitaryUnarmed'/>
        </enum-item>
        <enum-item name='GRASP_STRIKE'>
            <item-attr name='caption' value='Striking'/>
            <item-attr name='caption_noun' value='Striker'/>
            <item-attr name='type' value='MilitaryUnarmed'/>
        </enum-item>
        <enum-item name='STANCE_STRIKE'>
            <item-attr name='caption' value='Kicking'/>
            <item-attr name='caption_noun' value='Kicker'/>
            <item-attr name='type' value='MilitaryUnarmed'/>
        </enum-item>
        <enum-item name='DODGING'>
            <item-attr name='caption' value='Dodging'/>
            <item-attr name='caption_noun' value='Dodger'/>
            <item-attr name='type' value='MilitaryDefense'/>
        </enum-item>
        <enum-item name='MISC_WEAPON'>
            <item-attr name='caption' value='Misc. Object'/>
            <item-attr name='caption_noun' value='Misc. Object User'/>
            <item-attr name='type' value='MilitaryWeapon'/>
        </enum-item>
        <enum-item name='KNAPPING'>
            <item-attr name='caption' value='Knapping'/>
            <item-attr name='caption_noun' value='Knapper'/>
            <item-attr name='type' value='MilitaryMisc'/>
        </enum-item>
        <enum-item name='MILITARY_TACTICS'>
            <item-attr name='caption' value='Military Tactics'/>
            <item-attr name='caption_noun' value='Tactician'/>
        </enum-item>
        <enum-item name='SHEARING'>
            <item-attr name='caption' value='Shearing'/>
            <item-attr name='caption_noun' value='Shearer'/>
            <item-attr name='profession' value='SHEARER'/>
            <item-attr name='labor' value='SHEARER'/>
        </enum-item>

        -- 108

        <enum-item name='SPINNING'>
            <item-attr name='caption' value='Spinning'/>
            <item-attr name='caption_noun' value='Spinner'/>
            <item-attr name='profession' value='SPINNER'/>
            <item-attr name='labor' value='SPINNER'/>
        </enum-item>
        <enum-item name='POTTERY'>
            <item-attr name='caption' value='Pottery'/>
            <item-attr name='caption_noun' value='Potter'/>
            <item-attr name='profession' value='POTTER'/>
            <item-attr name='labor' value='POTTERY'/>
        </enum-item>
        <enum-item name='GLAZING'>
            <item-attr name='caption' value='Glazing'/>
            <item-attr name='caption_noun' value='Glazer'/>
            <item-attr name='profession' value='GLAZER'/>
            <item-attr name='labor' value='GLAZING'/>
        </enum-item>
        <enum-item name='PRESSING'>
            <item-attr name='caption' value='Pressing'/>
            <item-attr name='caption_noun' value='Presser'/>
            <item-attr name='profession' value='PRESSER'/>
            <item-attr name='labor' value='PRESSING'/>
        </enum-item>
        <enum-item name='BEEKEEPING'>
            <item-attr name='caption' value='Beekeeping'/>
            <item-attr name='caption_noun' value='Beekeeper'/>
            <item-attr name='profession' value='BEEKEEPER'/>
            <item-attr name='labor' value='BEEKEEPING'/>
        </enum-item>
        <enum-item name='WAX_WORKING'>
            <item-attr name='caption' value='Wax Working'/>
            <item-attr name='caption_noun' value='Wax Worker'/>
            <item-attr name='profession' value='WAX_WORKER'/>
            <item-attr name='labor' value='WAX_WORKING'/>
        </enum-item>
        <enum-item name='CLIMBING'>
            <item-attr name='caption' value='Climbing'/>
            <item-attr name='caption_noun' value='Climber'/>
            <item-attr name='type' value='Personal'/>
        </enum-item>
        <enum-item name='GELD'>
            <item-attr name='caption' value='Gelding'/>
            <item-attr name='caption_noun' value='Gelder'/>
            <item-attr name='profession' value='GELDER'/>
            <item-attr name='labor' value='GELD'/>
        </enum-item>
        <enum-item name='DANCE'>
            <item-attr name='caption' value='Dance'/>
            <item-attr name='caption_noun' value='Dancer'/>
            <item-attr name='profession' value='DANCER'/>
        </enum-item>
        <enum-item name='MAKE_MUSIC'>
            <item-attr name='caption' value='Music'/>
            <item-attr name='caption_noun' value='Musician'/>
            <item-attr name='profession' value='BARD'/>
        </enum-item>

        -- 118

        <!-- cannot be 'SING' because this causes a conflict with math.h -->
        <enum-item name='SING_MUSIC'>
            <item-attr name='caption' value='Singing'/>
            <item-attr name='caption_noun' value='Singer'/>
            <item-attr name='profession' value='BARD'/>
        </enum-item>
        <enum-item name='PLAY_KEYBOARD_INSTRUMENT'>
            <item-attr name='caption' value='Keyboard Instrument'/>
            <item-attr name='caption_noun' value='Keyboardist'/>
            <item-attr name='profession' value='BARD'/>
        </enum-item>
        <enum-item name='PLAY_STRINGED_INSTRUMENT'>
            <item-attr name='caption' value='Stringed Instrument'/>
            <item-attr name='caption_noun' value='Stringed Instrumentalist'/>
            <item-attr name='profession' value='BARD'/>
        </enum-item>
        <enum-item name='PLAY_WIND_INSTRUMENT'>
            <item-attr name='caption' value='Wind Instrument'/>
            <item-attr name='caption_noun' value='Wind Instrumentalist'/>
            <item-attr name='profession' value='BARD'/>
        </enum-item>
        <enum-item name='PLAY_PERCUSSION_INSTRUMENT'>
            <item-attr name='caption' value='Percussion Instrument'/>
            <item-attr name='caption_noun' value='Percussionist'/>
            <item-attr name='profession' value='BARD'/>
        </enum-item>
        <enum-item name='CRITICAL_THINKING'>
            <item-attr name='caption' value='Critical Thinking'/>
            <item-attr name='caption_noun' value='Critical Thinker'/>
        </enum-item>
        <enum-item name='LOGIC'>
            <item-attr name='caption' value='Logic'/>
            <item-attr name='caption_noun' value='Logician'/>
        </enum-item>
        <enum-item name='MATHEMATICS'>
            <item-attr name='caption' value='Mathematics'/>
            <item-attr name='caption_noun' value='Mathematician'/>
        </enum-item>
        <enum-item name='ASTRONOMY'>
            <item-attr name='caption' value='Astronomy'/>
            <item-attr name='caption_noun' value='Astronomer'/>
        </enum-item>
        <enum-item name='CHEMISTRY'>
            <item-attr name='caption' value='Chemistry'/>
            <item-attr name='caption_noun' value='Chemist'/>
        </enum-item>

        -- 128

        <enum-item name='GEOGRAPHY'>
            <item-attr name='caption' value='Geography'/>
            <item-attr name='caption_noun' value='Geographer'/>
        </enum-item>
        <enum-item name='OPTICS_ENGINEER'>
            <item-attr name='caption' value='Optics Engineer'/>
            <item-attr name='caption_noun' value='Optics Engineer'/>
        </enum-item>
        <enum-item name='FLUID_ENGINEER'>
            <item-attr name='caption' value='Fluid Engineer'/>
            <item-attr name='caption_noun' value='Fluid Engineer'/>
        </enum-item>
        <enum-item name='PAPERMAKING'>
            <item-attr name='caption' value='Papermaking'/>
            <item-attr name='caption_noun' value='Papermaker'/>
            <item-attr name='profession' value='PAPERMAKER'/>
            <item-attr name='labor' value='PAPERMAKING'/>
        </enum-item>
        <enum-item name='BOOKBINDING'>
            <item-attr name='caption' value='Bookbinding'/>
            <item-attr name='caption_noun' value='Bookbinder'/>
            <item-attr name='profession' value='BOOKBINDER'/>
            <item-attr name='labor' value='BOOKBINDING'/>
        </enum-item>
        <enum-item name='INTRIGUE'>
            <item-attr name='caption' value='Intrigue'/>
            <item-attr name='caption_noun' value='Schemer'/>
        </enum-item>
        <enum-item name='RIDING'>
            <item-attr name='caption' value='Riding'/>
            <item-attr name='caption_noun' value='Rider'/>
        </enum-item>

        <enum-item name='CUT_STONE'>
            <item-attr name='caption' value='Cut Stone'/>
            <item-attr name='caption_noun' value='Stonecutter'/>
            <item-attr name='labor' value='STONECUTTER'/>
        </enum-item>

        <enum-item name='CARVE_STONE'>
            <item-attr name='caption' value='Carve Stone'/>
            <item-attr name='caption_noun' value='Stonecarver'/>
            <item-attr name='labor' value='STONE_CARVER'/>
        </enum-item>

        <enum-item name='MODSKILL01'>
            <item-attr name='caption' value='Mod Skill 1'/>
            <item-attr name='caption_noun' value='Mod Skill 1'/>
        </enum-item>

        <enum-item name='MODSKILL02'>
            <item-attr name='caption' value='Mod Skill 2'/>
            <item-attr name='caption_noun' value='Mod Skill 2'/>
        </enum-item>

        <enum-item name='MODSKILL03'>
            <item-attr name='caption' value='Mod Skill 3'/>
            <item-attr name='caption_noun' value='Mod Skill 3'/>
        </enum-item>

        <enum-item name='MODSKILL04'>
            <item-attr name='caption' value='Mod Skill 4'/>
            <item-attr name='caption_noun' value='Mod Skill 4'/>
        </enum-item>

        <enum-item name='MODSKILL05'>
            <item-attr name='caption' value='Mod Skill 5'/>
            <item-attr name='caption_noun' value='Mod Skill 5'/>
        </enum-item>

        <enum-item name='MODSKILL06'>
            <item-attr name='caption' value='Mod Skill 6'/>
            <item-attr name='caption_noun' value='Mod Skill 6'/>
        </enum-item>

        <enum-item name='MODSKILL07'>
            <item-attr name='caption' value='Mod Skill 7'/>
            <item-attr name='caption_noun' value='Mod Skill 7'/>
        </enum-item>

        <enum-item name='MODSKILL08'>
            <item-attr name='caption' value='Mod Skill 8'/>
            <item-attr name='caption_noun' value='Mod Skill 8'/>
        </enum-item>

        <enum-item name='MODSKILL09'>
            <item-attr name='caption' value='Mod Skill 9'/>
            <item-attr name='caption_noun' value='Mod Skill 9'/>
        </enum-item>

        <enum-item name='MODSKILL10'>
            <item-attr name='caption' value='Mod Skill 10'/>
            <item-attr name='caption_noun' value='Mod Skill 10'/>
        </enum-item>

        <enum-item name='UNUSED_01'/>
        <enum-item name='UNUSED_02'/>

    </enum-type>
</data-definition>

<!--
Local Variables:
indent-tabs-mode: nil
nxml-child-indent: 4
End:
-->
