<data-definition>
    <global-object name="obj_98EDE30" offset="0x98ede30">
        <comment>ctor 0x804C78C [_ZNSt8ios_base4InitC1Ev]; dtor 0x804C3AC [_ZNSt8ios_base4InitD1Ev]</comment>
    </global-object>
    <global-object name="obj_8EB06A0" offset="0x8eb06a0" size="32">
        <comment>dtor 0x804C90C [_ZNSsD1Ev]</comment>
    </global-object>
    <!--<global-object name="gview" offset="0x8eb06c0" size="1812916">
        <comment>ctor 0x804C79C [_ZN11interfacestC1Ev]; dtor 0x804C51C [_ZN11interfacestD1Ev]</comment>
    </global-object>-->
    <global-object name="obj_906B074" offset="0x906b074" size="12">
        <comment>dtor 0x85CF710</comment>
    </global-object>
    <!--<global-object name="timed_events" offset="0x906b080" size="2144">
        <comment>dtor 0x85CF6B0</comment>
    </global-object>
    <global-object name="ui_build_selector" offset="0x906b8e0" size="6253408">
        <comment>dtor 0x85D06F0</comment>
    </global-object>
    <global-object name="ui_building_assign_type" offset="0x9662440" size="16">
        <comment>dtor 0x85CFCB0</comment>
    </global-object>
    <global-object name="ui_building_assign_is_marked" offset="0x9662450" size="16">
        <comment>dtor 0x85CFCB0</comment>
    </global-object>
    <global-object name="ui_building_assign_units" offset="0x9662460" size="16">
        <comment>dtor 0x85CFB10</comment>
    </global-object>
    <global-object name="ui_building_assign_items" offset="0x9662470" size="12">
        <comment>dtor 0x85CF980</comment>
    </global-object>-->
    <global-object name="obj_966247C" offset="0x966247c" size="12">
        <comment>dtor 0x85CF830</comment>
    </global-object>
    <global-object name="obj_9662488" offset="0x9662488" size="12">
        <comment>dtor 0x85CFCE0</comment>
    </global-object>
    <global-object name="obj_9662494" offset="0x9662494" size="124">
        <comment>dtor 0x85CFCE0</comment>
    </global-object>
    <global-object name="obj_9662510" offset="0x9662510" size="16">
        <comment>dtor 0x85CFCE0</comment>
    </global-object>
    <global-object name="obj_9662520" offset="0x9662520" size="16">
        <comment>dtor 0x85CFCE0</comment>
    </global-object>
    <global-object name="obj_9662530" offset="0x9662530" size="16">
        <comment>dtor 0x85CFCE0</comment>
    </global-object>
    <global-object name="obj_9662540" offset="0x9662540" size="16">
        <comment>dtor 0x85CFCE0</comment>
    </global-object>
    <global-object name="obj_9662550" offset="0x9662550" size="16">
        <comment>dtor 0x85CFD70</comment>
    </global-object>
    <!--<global-object name="ui" offset="0x9662560" size="28448">
        <comment>ctor 0x87DB0A0; dtor 0x85DEA70</comment>
    </global-object>
    <global-object name="ui_advmode" offset="0x9669480" size="480">
        <comment>dtor 0x85E0390</comment>
    </global-object>
    <global-object name="world" offset="0x9669660" size="1652064">
        <comment>ctor 0x804BE2C [_Znaj]; ctor 0x804C0CC [_ZdaPv]; ctor 0x88F5B40; ctor 0x804C85C [_ZNSs6assignEPKcj]; ctor 0x804C85C [_ZNSs6assignEPKcj]; ctor 0x804C85C [_ZNSs6assignEPKcj]; ctor 0x804C85C [_ZNSs6assignEPKcj]; dtor 0x8B93ED0</comment>
    </global-object>
    <global-object name="ui_sidebar_menus" offset="0x97fcbc0" size="6208">
        <comment>dtor 0x85E0990</comment>
    </global-object>
    <global-object name="cursor_unit_list" offset="0x97fe400" size="65600">
        <comment>dtor 0x85CFB40</comment>
    </global-object>-->
    <global-object name="obj_980E440" offset="0x980e440" size="64">
        <comment>dtor 0x85D4510</comment>
    </global-object>
    <!--<global-object name="init" offset="0x980e480" size="4256">
        <comment>ctor 0x804BE2C [_Znaj]; ctor 0x804BE2C [_Znaj]; ctor 0x804BE2C [_Znaj]; ctor 0x804C48C [_ZN14init_displaystC1Ev]; dtor 0x85CF860</comment>
    </global-object>
    <global-object name="d_init" offset="0x980f520" size="525856">
        <comment>ctor 0x804BE2C [_Znaj]; ctor 0x804BE2C [_Znaj]; ctor 0x804BE2C [_Znaj]; ctor 0x81EC310; dtor 0x85CF8F0</comment>
    </global-object>
    <global-object name="ui_look_list" offset="0x988fb40" size="44">
        <comment>dtor 0x85CF6E0</comment>
    </global-object>-->
    <global-object name="obj_988FB6C" offset="0x988fb6c" size="12">
        <comment>dtor 0x85CF980</comment>
    </global-object>
    <global-object name="obj_988FB78" offset="0x988fb78" size="12">
        <comment>dtor 0x85CF740</comment>
    </global-object>
    <global-object name="obj_988FB84" offset="0x988fb84" size="12">
        <comment>dtor 0x85CFD70</comment>
    </global-object>
    <global-object name="obj_988FB90" offset="0x988fb90" size="12">
        <comment>dtor 0x85CFD70</comment>
    </global-object>
    <global-object name="obj_988FB9C" offset="0x988fb9c" size="20">
        <comment>dtor 0x85CFD70</comment>
    </global-object>
    <global-object name="obj_988FBB0" offset="0x988fbb0">
        <comment>dtor 0x85CFB10</comment>
    </global-object>
</data-definition>

<!--
Local Variables:
indent-tabs-mode: nil
nxml-child-indent: 4
End:
-->
